nefertem_metric/__init__.py
nefertem_metric/metadata/__init__.py
nefertem_metric/metadata/report.py
nefertem_metric/plugins/__init__.py
nefertem_metric/plugins/builder.py
nefertem_metric/plugins/metric.py
nefertem_metric/plugins/plugin.py
nefertem_metric/run/__init__.py
nefertem_metric/run/run.py
nefertem_metric-2.0.0.dist-info/LICENSE.txt
nefertem_metric-2.0.0.dist-info/METADATA
nefertem_metric-2.0.0.dist-info/WHEEL
nefertem_metric-2.0.0.dist-info/top_level.txt
nefertem_metric-2.0.0.dist-info/RECORD
