Metadata-Version: 2.1
Name: nefertem-metric
Version: 2.0.0
Summary: Python data validation library
Author-email: Fondazione Bruno Kessler <dslab@fbk.eu>, Matteo Martini <mmartini@fbk.eu>
License: Apache License
Project-URL: Homepage, https://github.com/scc-digitalhub/nefertem
Keywords: data,validation,quality
Classifier: License :: OSI Approved :: Apache Software License
Classifier: Programming Language :: Python :: 3.9
Classifier: Programming Language :: Python :: 3.10
Classifier: Programming Language :: Python :: 3.11
Requires-Python: >=3.9
License-File: LICENSE.txt
Requires-Dist: nefertem-core ~=2.0
